{"stanza": ["De ti, Jesus, Senhor,\nEu tenho precis\u00e3o;\nS\u00f3 teu divino amor\nD\u00e1 paz ao cora\u00e7\u00e3o.", "\u00d3 meu Jesus, comigo\nVem estar agora,\nT\u00e9 que no c\u00e9u contigo\nEu v\u00e1 morar.", "Oh, d\u00e1-me, meu Jesus,\nFruir teu rico amor,\nE andar em tua luz,\nSubmisso a ti, Senhor!", "Vencendo a tenta\u00e7\u00e3o,\nContente viverei\nSob tua prote\u00e7\u00e3o,\n\u00d3 meu bendito Rei!"], "refrain": true, "authors": {"lyrics": ["Annie Sherwood Hawks (1835-1918)"], "melody": ["Robert Lowry (1826-1899)"], "translation": ["Alexander Latimer Blackford (1829-1890)"]}}