{"stanza": ["Ceifeiros da seara santa\nSois poucos, d\u00e9beis sois;\nPor\u00e9m, \u00e9 forte vosso Mestre;\nAvante! Avante, pois!", "Os que confiam no Senhor, obter\u00e3o vigor,\nFor\u00e7as novas h\u00e3o de ter, subir\u00e3o at\u00e9 as alturas,\nAndar\u00e3o alegres sempre, correr\u00e3o sem se cansar,\nAndar\u00e3o alegres sempre, correr\u00e3o sem se cansar.\nCorrer\u00e3o e sem fadiga, como \u00e1guias voar\u00e3o.", "Cansados, tristes, sem alento,\nDeixai de lamentar;\nPor v\u00f3s est\u00e1 Jesus, o Mestre;\nPor que desanimar?", "Jesus est\u00e1 conosco sempre\nNa luta contra o mal;\nCoragem, pois, irm\u00e3os, avante\nNa obra sem igual!"], "refrain": true, "authors": {"lyrics": ["James McGranahan (1840-1907)"], "melody": ["James McGranahan (1840-1907)"], "translation": ["William Edwin Entzminger (1859-1930)"]}}